pyhoroscope/__init__.py
pyhoroscope/horoscope.py
PyHoroscope-1.0.0.dist-info/LICENSE
PyHoroscope-1.0.0.dist-info/METADATA
PyHoroscope-1.0.0.dist-info/WHEEL
PyHoroscope-1.0.0.dist-info/entry_points.txt
PyHoroscope-1.0.0.dist-info/top_level.txt
PyHoroscope-1.0.0.dist-info/RECORD
