Metadata-Version: 2.1
Name: PyHoroscope
Version: 1.0.0
Summary: Get The Horoscope Details For Your Sign
Home-page: https://github.com/fahad-programmer/pyhoroscope
Author: Fahad Malik, Imran Akbar
Author-email: infotainer@gmail.com
License: MIT
Platform: UNKNOWN
Classifier: License :: OSI Approved :: MIT License
Classifier: Programming Language :: Python :: 3
Classifier: Programming Language :: Python :: 3.7
Requires-Dist: bs4
Requires-Dist: requests
Requires-Dist: lxml
